[
  {
    "key": "t0001",
    "spec": {
      "tag": "h1",
      "id": null,
      "classes": [
        "title"
      ]
    },
    "occurrence": 1,
    "expected_text": "Диплом",
    "line_hint": null
  },
  {
    "key": "t0002",
    "spec": {
      "tag": "p",
      "id": null,
      "classes": [
        "text"
      ]
    },
    "occurrence": 1,
    "expected_text": "Настоящим подтверждается, что",
    "line_hint": null
  },
  {
    "key": "t0003",
    "spec": {
      "tag": "p",
      "id": null,
      "classes": [
        "text",
        "message"
      ]
    },
    "occurrence": 1,
    "expected_text": "является официальным партнёром компании LICANT и может осуществлять поставку продуктов PartnerOS и LICANT-IT.",
    "line_hint": null
  },
  {
    "key": "t0004",
    "spec": {
      "tag": "span",
      "id": null,
      "classes": [
        "ceo"
      ]
    },
    "occurrence": 1,
    "expected_text": "Фенёв C.В.",
    "line_hint": null
  },
  {
    "key": "t0005",
    "spec": {
      "tag": "div",
      "id": null,
      "classes": []
    },
    "occurrence": 1,
    "expected_text": "Генеральный директор ООО «Ликант» Дата",
    "line_hint": null
  },
  {
    "key": "t0006",
    "spec": {
      "tag": "span",
      "id": null,
      "classes": [
        "subtitle"
      ]
    },
    "occurrence": 1,
    "expected_text": "Генеральный директор ООО «Ликант»",
    "line_hint": null
  },
  {
    "key": "t0007",
    "spec": {
      "tag": "span",
      "id": null,
      "classes": [
        "subtitle"
      ]
    },
    "occurrence": 2,
    "expected_text": "Дата",
    "line_hint": null
  }
]